ez_context.py
ez_context-1.0.2.dist-info/LICENSE
ez_context-1.0.2.dist-info/METADATA
ez_context-1.0.2.dist-info/WHEEL
ez_context-1.0.2.dist-info/top_level.txt
ez_context-1.0.2.dist-info/RECORD
