Metadata-Version: 2.1
Name: ez_context
Version: 1.0.2
Summary: An ez generator-based context manager
Author-email: Marckie Zeender <mkzeender@gmail.com>
Project-URL: Homepage, https://github.com/mkzeender/ez_context
Project-URL: Issues, https://github.com/mkzeender/ez_context/issues
Classifier: Programming Language :: Python :: 3
Classifier: License :: OSI Approved :: MIT License
Classifier: Operating System :: OS Independent
Requires-Python: >=3.12
License-File: LICENSE
